odoo/addons/printing_auto_base/README.rst
odoo/addons/printing_auto_base/__init__.py
odoo/addons/printing_auto_base/__manifest__.py
odoo/addons/printing_auto_base/i18n/it.po
odoo/addons/printing_auto_base/i18n/printing_auto_base.pot
odoo/addons/printing_auto_base/models/__init__.py
odoo/addons/printing_auto_base/models/printing_auto.py
odoo/addons/printing_auto_base/models/printing_auto_mixin.py
odoo/addons/printing_auto_base/readme/CONTRIBUTORS.md
odoo/addons/printing_auto_base/readme/DESCRIPTION.md
odoo/addons/printing_auto_base/security/ir.model.access.csv
odoo/addons/printing_auto_base/static/description/icon.png
odoo/addons/printing_auto_base/static/description/index.html
odoo/addons/printing_auto_base/tests/__init__.py
odoo/addons/printing_auto_base/tests/common.py
odoo/addons/printing_auto_base/tests/model_test.py
odoo/addons/printing_auto_base/tests/test_printing_auto_base.py
odoo/addons/printing_auto_base/views/printing_auto.xml
odoo_addon_printing_auto_base-18.0.1.2.0.2.dist-info/METADATA
odoo_addon_printing_auto_base-18.0.1.2.0.2.dist-info/WHEEL
odoo_addon_printing_auto_base-18.0.1.2.0.2.dist-info/top_level.txt
odoo_addon_printing_auto_base-18.0.1.2.0.2.dist-info/RECORD
