Metadata-Version: 2.1
Name: odoo-addon-printing_auto_base
Version: 18.0.1.2.0.2
Requires-Python: >=3.10
Requires-Dist: odoo-addon-base_report_to_printer==18.0.*
Requires-Dist: odoo==18.0.*
Summary: Printing Auto Base
Home-page: https://github.com/OCA/report-print-send
License: AGPL-3
Author: BCIM, MT Software, Odoo Community Association (OCA)
Author-email: support@odoo-community.org
Classifier: Programming Language :: Python
Classifier: Framework :: Odoo
Classifier: Framework :: Odoo :: 18.0
Classifier: License :: OSI Approved :: GNU Affero General Public License v3
